wq_pypi_demo
