Metadata-Version: 1.1
Name: wq-setup-demo
Version: 1.1.0.dev1
Summary: 测试打包上传pip
Home-page: https://github.com/13126655557/wq_pyspider.git
Author: wangquan
Author-email: 13126655557@163.com
License: MIT
Keywords: wq project python
Platform: UNKNOWN
Classifier: Development Status :: 4 - Beta
Classifier: Intended Audience :: Developers
Classifier: Topic :: Software Development :: Build Tools
Classifier: License :: OSI Approved :: MIT License
Classifier: Programming Language :: Python :: 2.6
Classifier: Programming Language :: Python :: 2.7
Classifier: Programming Language :: Python :: 3
Classifier: Programming Language :: Python :: 3.3
Classifier: Programming Language :: Python :: 3.4
Classifier: Programming Language :: Python :: 3.5
